Workbook

Sheet 已花成本
A1: 开发期已花成本（项目 2026-04 启动）
A3: 类别 | B3: 金额（USD） | C3: 说明
A4: 开发外包 | B4: =SUMIF(支出明细!B:B,"开发外包",支出明细!D:D) -> 6700 | C4: 7 周外包开发（4 月 7 期 + 5 月 3 期）：MVP 脚手架 / 订单核心 / 代理产品 / 动态定价 / AI 助手 / 演示包 / 反馈迭代
A5: Claude Code | B5: =SUMIF(支出明细!B:B,"Claude Code",支出明细!D:D) -> 130 | C5: 开发主力 AI 工具：Anthropic API token 用量（4 月 $50 + 5 月 $80）
A6: OpenAI / 模型测试 | B6: =SUMIF(支出明细!B:B,"OpenAI",支出明细!D:D) -> 130 | C6: AI 助手内嵌的模型调用 + Prompt 迭代调试（4 月 $100 + 5 月 $30）
A7: 服务器（阿里云 HK） | B7: =SUMIF(支出明细!B:B,"服务器",支出明细!D:D) -> 64 | C7: 4C8G 轻量实例 $32/月 × 2 期（4 月 + 5 月）
A8: 域名 + DNS | B8: =SUMIF(支出明细!B:B,"域名",支出明细!D:D) -> 50 | C8: citur.com 试注 + 备用 .cn 域名 + Cloudflare 免费层 DNS
A9: GitHub / CI | B9: =SUMIF(支出明细!B:B,"GitHub",支出明细!D:D) -> 40 | C9: Actions 分钟数（CI 流水线 ~30k 分钟）
A10: 设计素材 | B10: =SUMIF(支出明细!B:B,"设计",支出明细!D:D) -> 80 | C10: Figma Pro 1 个月 + Iconify 图标一次性
A11: 杂项 | B11: =SUMIF(支出明细!B:B,"杂项",支出明细!D:D) -> 140 | C11: Unsplash CDN + Google Fonts 商用授权 + 越南语人工校对
A12: 合计（已花） | B12: =支出明细!D27 -> 7334

Sheet 支出明细
A1: 支出明细（按时间正序）— 项目 2026-04 启动
A2: 注：所有金额为估算（无真实发票对照）。每月底加新行。
A4: 日期 | B4: 类别 | C4: 供应商 / 项目 | D4: 金额 (USD) | E4: 具体买了什么 | F4: 工时备注
A5: ═══ 2026-04：项目启动 + MVP + AI 助手 ═══
A6: 2026-04-02 | B6: 开发外包 | C6: Phase 1 MVP | D6: 800 | E6: monorepo 脚手架（backend/sales-web/admin-web/miniprogram）+ Prisma schema + JWT/RBAC 4 角色 + 微信 stub | F6: ~50h
A7: 2026-04-09 | B7: 开发外包 | C7: Phase 1 订单核心 | D7: 900 | E7: Order/OrderItem/Passenger 模型 + 13 状态机 + 航班搜索 + 座位库存 CAS + 退款报价 | F7: ~55h
A8: 2026-04-15 | B8: 开发外包 | C8: Phase 1 代理+产品 | D8: 850 | E8: 3 级代理层级 + 佣金分账 + Hotels/Transfers/Visas/Bundles CRUD | F8: ~50h
A9: 2026-04-18 | B9: 服务器 | C9: 阿里云 HK | D9: 32 | E9: 4C8G 轻量实例首月（包月 $32）
A10: 2026-04-19 | B10: 域名 | C10: Namecheap + 阿里云 | D10: 50 | E10: citur.com 试注 + 备用 .cn 域名 + Cloudflare 免费层 DNS
A11: 2026-04-22 | B11: 开发外包 | C11: Phase 2 动态定价 | D11: 800 | E11: 动态定价引擎：DateRanking A/B/C/D × 余位 18 buckets；PricingService；结算单 + 月度报表 | F11: ~50h
A12: 2026-04-25 | B12: 开发外包 | C12: Phase 2 AI 助手 | D12: 1000 | E12: AI 助手 v1：5 个 tool（search_flights/hotels/transfers/visas/bundles）+ propose_order + 多轮对话循环 | F12: ~60h
A13: 2026-04-26 | B13: OpenAI | C13: OpenAI API | D13: 100 | E13: AI 助手 Prompt 迭代 + GPT-5-mini vs Claude Sonnet 对比 + tool-use 调试
A14: 2026-04-27 | B14: 杂项 | C14: Unsplash + Google Fonts | D14: 60 | E14: 酒店/接送/签证产品图（25 张 hero）+ Inter / Noto Sans 商用授权
A15: 2026-04-28 | B15: 设计 | C15: Figma + Iconify | D15: 80 | E15: Figma Pro 1 个月 + 一些图标包（一次性买断）
A16: 2026-04-28 | B16: 开发外包 | C16: Phase 2 演示准备 | D16: 750 | E16: 小程序 (Taro 4.0.9) + 微信支付 sandbox + i18n 完善 + Demo seed 6 单 + 演示包 | F16: ~45h
A17: 2026-04-29 | B17: GitHub | C17: GitHub Actions | D17: 40 | E17: CI 流水线（lint/test/build/docker push）~30k 分钟
A18: 2026-04-29 | B18: 杂项 | C18: 人工翻译 | D18: 80 | E18: 越南语 + 英语 i18n 文案人工校对
A19: 2026-04-29 | B19: Claude Code | C19: Anthropic API | D19: 50 | E19: Claude Code 试用期 token 用量（开发主力工具）
A20: ═══ 2026-05：反馈驱动迭代 ═══
A21: 2026-05-05 | B21: 开发外包 | C21: M2 完善 | D21: 400 | E21: M2 路由表 + 跨域代理 RBAC + agents.routes 完整覆盖 + 演示包 docx/pptx 生成脚本 | F21: ~25h
A22: 2026-05-13 | B22: 开发外包 | C22: 小程序修复 | D22: 300 | E22: 小程序 build 通：webpack@5.91 pin + Node 22 兼容 + dev.ts 指 staging + Taro 配置修 | F22: ~18h
A23: 2026-05-13 | B23: 服务器 | C23: 阿里云 HK | D23: 32 | E23: 第 2 月（4-5 月共 $64）
A24: 2026-05-14 | B24: OpenAI | C24: OpenAI API | D24: 30 | E24: 测试 staging AI 调用（地区屏蔽前的小额）
A25: 2026-05-14 | B25: Claude Code | C25: Anthropic API | D25: 80 | E25: 5 月 Claude Code token 用量（持续开发用）
A26: 2026-05-20 | B26: 开发外包 | C26: 反馈 wave 1 | D26: 900 | E26: PNR Excel 导出 / 护照 zip 打包 / 待办系统 / 17 字段扩展 / 拼房 endpoint / claim 接单 | F26: ~55h
A27: ═══ 合计 ═══ | D27: =SUM(D5:D26) -> 7334

Sheet 月成本预估
A1: 投产后月成本预估（3 阶段）
A3: 蓝色 = 假设输入；黑色 = 公式合计；金额单位：USD/月
A5: 类别 | B5: A · 内部测试期 | C5: B · 公测期 (~500 客户) | D5: C · 稳定期 (~5000 客户) | E5: 说明
A6: AI / Token | B6: 35 | C6: 550 | D6: 3500 | E6: 对话量×单价；A: 50-200/天 ｜ B: 500-1500/天 ｜ C: 3000-8000/天
A7: 服务器 | B7: 32 | C7: 100 | D7: 250 | E7: 阿里云 HK 4C8G → 8C16G + 备份机 → 主从 + worker
A8: 数据库（独立 RDS） | B8: 0 | C8: 50 | D8: 150 | E8: B 起独立 4G；C 主从 + 自动备份
A9: CDN（Cloudflare） | B9: 0 | C9: 20 | D9: 100 | E9: 免费 → Pro $20 → Business $200，按流量分级
A10: 邮件 / 短信 | B10: 0 | C10: 100 | D10: 600 | E10: 阿里云通信 / Twilio 按量计费
A11: 监控（Sentry + 日志） | B11: 0 | C11: 30 | D11: 100 | E11: Team plan + 日志聚合
A12: 其他（域名/SSL/备份） | B12: 5 | C12: 20 | D12: 50 | E12: 域名续费、SSL 免费、备份外发
A13: 月成本合计 | B13: =SUM(B6:B12) -> 72 | C13: =SUM(C6:C12) -> 870 | D13: =SUM(D6:D12) -> 4750
A14: × 12 月（年） | B14: =B13*12 -> 864 | C14: =C13*12 -> 10440 | D14: =D13*12 -> 57000

Sheet AI Token 成本
A1: AI 单次对话成本（Claude Sonnet 4.6 定价）
A3: 定价（USD per 1M tokens）
A4: 输入 token | B4: 3
A5: 输出 token | B5: 15
A6: 缓存读取（输入打 9 折） | B6: 0.3
A8: 单次对话假设（5 个轮次平均）
A9: 输入 tokens（无缓存） | B9: 10000
A10: 输入 tokens（缓存命中） | B10: 9000
A11: 输入 tokens（缓存未命中） | B11: 1000
A12: 输出 tokens | B12: 2500
A14: 成本计算
A15: 不带 prompt caching
A16: 输入成本 | B16: =B9*B4/1000000 -> 0.03
A17: 输出成本 | B17: =B12*B5/1000000 -> 0.0375
A18: 对话总成本（无缓存） | B18: =B16+B17 -> 0.0675
A20: 启用 prompt caching
A21: 缓存读取成本 | B21: =B10*B6/1000000 -> 0.0027
A22: 全价输入成本 | B22: =B11*B4/1000000 -> 0.003
A23: 输出成本 | B23: =B12*B5/1000000 -> 0.0375
A24: 对话总成本（含缓存） | B24: =B21+B22+B23 -> 0.0432
A25: 省下 | B25: =1-B24/B18 -> 0.36
A27: 对话量 → 月成本预估（含缓存）
A28: 对话/天 | B28: 对话/月 | C28: 月成本（USD） | D28: 年成本（USD）
A29: 50 | B29: =A29*30 -> 1500 | C29: =B29*$B$24 -> 64.8 | D29: =C29*12 -> 777.6
A30: 200 | B30: =A30*30 -> 6000 | C30: =B30*$B$24 -> 259.2 | D30: =C30*12 -> 3110.4
A31: 500 | B31: =A31*30 -> 15000 | C31: =B31*$B$24 -> 648 | D31: =C31*12 -> 7776
A32: 1000 | B32: =A32*30 -> 30000 | C32: =B32*$B$24 -> 1296 | D32: =C32*12 -> 15552
A33: 2000 | B33: =A33*30 -> 60000 | C33: =B33*$B$24 -> 2592 | D33: =C33*12 -> 31104
A34: 5000 | B34: =A34*30 -> 150000 | C34: =B34*$B$24 -> 6480 | D34: =C34*12 -> 77760
A35: 8000 | B35: =A35*30 -> 240000 | C35: =B35*$B$24 -> 10368 | D35: =C35*12 -> 124416

Sheet 单位经济学
A1: 单位经济学（成本 vs 收入）
A3: 蓝色 = 假设；黑色 = 公式；绿色 = 跨表引用
A5: 汇率 CNY → USD | B5: 0.14
A6: 平台抽成率 | B6: 0.08
A8: 阶段 | B8: 月单量 | C8: 客单价（¥） | D8: 月 GMV（¥） | E8: 月毛利（¥） | F8: 月毛利（$）
A9: 公测期 | B9: 100 | C9: 3500 | D9: =B9*C9 -> 350000 | E9: =D9*$B$6 -> 28000 | F9: =E9*$B$5 -> 3920
A10: 稳定期 | B10: 1000 | C10: 3800 | D10: =B10*C10 -> 3800000 | E10: =D10*$B$6 -> 304000 | F10: =E10*$B$5 -> 42560
A11: 规模化 | B11: 5000 | C11: 4000 | D11: =B11*C11 -> 20000000 | E11: =D11*$B$6 -> 1600000 | F11: =E11*$B$5 -> 224000
A14: 成本覆盖比
A15: 阶段 | B15: 月毛利（$） | C15: 月成本（$） | D15: 覆盖倍数 | E15: 毛利率（毛利/GMV）
A16: 公测期 | B16: =F9 -> 3920 | C16: =月成本预估!C13 -> 870 | D16: =B16/C16 -> 4.5057471 | E16: =E9/D9 -> 0.08
A17: 稳定期 | B17: =F10 -> 42560 | C17: =月成本预估!D13 -> 4750 | D17: =B17/C17 -> 8.96 | E17: =E10/D10 -> 0.08
A18: 规模化 | B18: =F11 -> 224000 | C18: =月成本预估!D13*1.5 -> 7125 | D18: =B18/C18 -> 31.438596 | E18: =E11/D11 -> 0.08
A20: 结论：单位经济学健康。关键不是控成本，是订单量做起来。
